solaredge_local/__init__.py
solaredge_local/information_pb2.py
solaredge_local/maintenance_pb2.py
solaredge_local/powercontrol_pb2.py
solaredge_local/solaredge.py
solaredge_local/status_pb2.py
solaredge_local-0.2.0.dist-info/METADATA
solaredge_local-0.2.0.dist-info/WHEEL
solaredge_local-0.2.0.dist-info/top_level.txt
solaredge_local-0.2.0.dist-info/RECORD
