Metadata-Version: 2.1
Name: solaredge-local
Version: 0.2.0
Summary: API wrapper to communicate locally with SolarEdge Inverters
Home-page: https://github.com/drobtravels/solaredge-local
Author: David Roberts
Author-email: 
License: MIT License
Platform: any
Classifier: Programming Language :: Python :: 3
Classifier: Development Status :: 4 - Beta
Classifier: Natural Language :: English
Classifier: Intended Audience :: Developers
Classifier: License :: OSI Approved :: MIT License
Classifier: Operating System :: OS Independent
Requires-Python: >=3.0
Requires-Dist: uplink
Requires-Dist: uplink-protobuf
